unreal_mcp_server.py
blueprint_action_tools/__init__.py
blueprint_action_tools/blueprint_action_tools.py
blueprint_tools/__init__.py
blueprint_tools/blueprint_tools.py
datatable_tools/__init__.py
datatable_tools/datatable_tools.py
docs/umg_transparency_guide.md
download_tools/__init__.py
download_tools/download_tools.py
editor_tools/__init__.py
editor_tools/editor_tools.py
executor_tools/__init__.py
executor_tools/command_line_executor_tools.py
executor_tools/python_executor_tools.py
gamewave_unreal_mcp-0.1.10.dist-info/licenses/LICENSE
material_tools/__init__.py
material_tools/material_tools.py
node_tools/__init__.py
node_tools/node_tools.py
pcg_tools/__init__.py
pcg_tools/pcg_tools.py
project_tools/__init__.py
project_tools/project_tools.py
scripts/actors/test_cube.py
scripts/blueprints/test_create_and_spawn_blueprints_with_different_components.py
scripts/blueprints/test_create_and_spawn_cube_blueprint.py
scripts/node/test_component_reference.py
scripts/node/test_create_bird_blueprint_with_input_and_camera.py
scripts/node/test_input_mapping.py
scripts/node/test_physics_variables.py
umg_tools/__init__.py
umg_tools/umg_tools.py
utils/__init__.py
utils/unreal_connection_utils.py
utils/blueprint_actions/__init__.py
utils/blueprint_actions/blueprint_action_operations.py
utils/blueprints/blueprint_operations.py
utils/datatable/datatable_utils.py
utils/editor/editor_operations.py
utils/executor/__init__.py
utils/executor/command_line_operations.py
utils/executor/python_executor_operations.py
utils/nodes/node_operations.py
utils/project/struct_operations.py
utils/widgets/widget_components.py
gamewave_unreal_mcp-0.1.10.dist-info/METADATA
gamewave_unreal_mcp-0.1.10.dist-info/WHEEL
gamewave_unreal_mcp-0.1.10.dist-info/entry_points.txt
gamewave_unreal_mcp-0.1.10.dist-info/top_level.txt
gamewave_unreal_mcp-0.1.10.dist-info/RECORD
