Metadata-Version: 2.4
Name: gamewave-unreal-mcp
Version: 0.1.10
Summary: Unreal MCP Server: The most advanced and powerful server for Unreal Engine integration via the Model Context Protocol (MCP).
Author-email: GameWave <fridayue5@gmail.com>
License: GNU GENERAL PUBLIC LICENSE
Project-URL: Homepage, https://gamewave.dev
Project-URL: Support, https://discord.gg/3q88TDTUTS
Keywords: unreal,engine,ue5,mcp,model,context,protocol,blueprint,umg,automation
Classifier: Programming Language :: Python :: 3
Classifier: Programming Language :: Python :: 3.10
Classifier: Programming Language :: Python :: 3.11
Classifier: Programming Language :: Python :: 3.12
Classifier: Operating System :: OS Independent
Classifier: Development Status :: 4 - Beta
Classifier: Intended Audience :: Developers
Classifier: Topic :: Software Development :: Libraries :: Python Modules
Classifier: Topic :: Games/Entertainment
Classifier: Topic :: Multimedia :: Graphics :: 3D Modeling
Requires-Python: >=3.10
License-File: LICENSE
Requires-Dist: mcp[cli]>=1.4.1
Requires-Dist: fastmcp>=0.2.0
Requires-Dist: uvicorn
Requires-Dist: fastapi
Requires-Dist: pydantic>=2.6.1
Requires-Dist: requests
Requires-Dist: objaverse
Dynamic: license-file
